render_engine_lunr/__init__.py
render_engine_lunr/plugins.py
render_engine_lunr/theme.py
render_engine_lunr/templates/components/lunrjs/lunr_search.html
render_engine_lunr/templates/components/lunrjs/lunrjs_head.html
render_engine_lunr-2024.1.1b3.dist-info/METADATA
render_engine_lunr-2024.1.1b3.dist-info/WHEEL
render_engine_lunr-2024.1.1b3.dist-info/top_level.txt
render_engine_lunr-2024.1.1b3.dist-info/RECORD
