Metadata-Version: 2.1
Name: render_engine_lunr
Version: 2024.1.1b3
Summary: Plugin and theme for Lunr.js
Project-URL: homepage, https://github.com/kjaymiller/render_engine_lunr
Project-URL: repository, https://github.com/kjaymiller/render_engine_lunr
Project-URL: documentation, https://github.io/kjaymiller/render_engine_lunr
Requires-Dist: jinja2
Requires-Dist: render-engine >=2024.1.1b1
Requires-Dist: lunr
Provides-Extra: dev
Requires-Dist: pytest ; extra == 'dev'
Requires-Dist: pytest-cov ; extra == 'dev'
Requires-Dist: pytest-playwright ; extra == 'dev'
Requires-Dist: ruff ; extra == 'dev'
